README.rst
setup.py
penkit_optimize/__init__.py
penkit_optimize/cli.py
penkit_optimize/greedy.py
penkit_optimize/path_graph.py
penkit_optimize/path_index.py
penkit_optimize/route_util.py
penkit_optimize/svg.py
penkit_optimize/visualize.py
penkit_optimize/vrp_solver.py
penkit_optimize.egg-info/PKG-INFO
penkit_optimize.egg-info/SOURCES.txt
penkit_optimize.egg-info/dependency_links.txt
penkit_optimize.egg-info/entry_points.txt
penkit_optimize.egg-info/requires.txt
penkit_optimize.egg-info/top_level.txt