Metadata-Version: 1.0
Name: penkit-optimize
Version: 0.0.3
Summary: Experimental SVG optimizer using or-tools.
Home-page: https://github.com/paulgb/penkit/optimizer
Author: Paul Butler
Author-email: penkit@paulbutler.org
License: UNKNOWN
Platform: UNKNOWN
